taskgpt/__init__.py
taskgpt/agent.py
taskgpt/cli.py
taskgpt/setup_env.py
taskgpt-0.1.5.dist-info/METADATA
taskgpt-0.1.5.dist-info/WHEEL
taskgpt-0.1.5.dist-info/entry_points.txt
taskgpt-0.1.5.dist-info/top_level.txt
taskgpt-0.1.5.dist-info/RECORD
