Metadata-Version: 2.4
Name: taskgpt
Version: 0.1.5
Summary: A CLI tool that helps you run GPT-based agents locally
Author: Ketan Hegde
Classifier: Programming Language :: Python :: 3
Classifier: Operating System :: OS Independent
Requires-Dist: requests
Requires-Dist: python-dotenv
Dynamic: author
Dynamic: classifier
Dynamic: description
Dynamic: description-content-type
Dynamic: requires-dist
Dynamic: summary
